{"loss": 0.17877813583457625, "timestamp": 1744381390, "checkpoint_dir_name": null, "done": false, "training_iteration": 1, "trial_id": "40a6d_00091", "date": "2025-04-11_15-23-10", "time_this_iter_s": 42.50664472579956, "time_total_s": 42.50664472579956, "pid": 9032, "hostname": "1B-C11-WINDOWS", "node_ip": "127.0.0.1", "config": {"optimizer": "sgd", "lr": 9.1825769497655e-05, "weight_decay": 0.0009879428292723944, "momentum": 0.2661326516171719}, "time_since_restore": 42.50664472579956, "iterations_since_restore": 1}
