{"loss": 0.45259035001327463, "timestamp": 1744375916, "checkpoint_dir_name": null, "done": false, "training_iteration": 1, "trial_id": "64db8_00002", "date": "2025-04-11_13-51-56", "time_this_iter_s": 43.21918869018555, "time_total_s": 43.21918869018555, "pid": 25432, "hostname": "1B-C12-WINDOWS", "node_ip": "127.0.0.1", "config": {"loss": "dice", "include_background": false, "squared_pred": true, "gamma": 3.2704412658046604, "alpha": 0.5533065082439226, "beta": 0.45435248485717294}, "time_since_restore": 43.21918869018555, "iterations_since_restore": 1}
